pf2e_wealth_calculator/__init__.py
pf2e_wealth_calculator/dataframes.py
pf2e_wealth_calculator/entry_point.py
pf2e_wealth_calculator/pf2ewc.py
pf2e_wealth_calculator/structs.py
pf2e_wealth_calculator/tables/materials.csv
pf2e_wealth_calculator/tables/PF2eItemList.csv
pf2e_wealth_calculator/tables/rune_replacer.csv
pf2e_wealth_calculator/tables/runes.csv
pf2e_wealth_calculator/tables/treasurebylevel.csv
pf2e_wealth_calculator-0.2.0.dist-info/entry_points.txt
pf2e_wealth_calculator-0.2.0.dist-info/LICENSE
pf2e_wealth_calculator-0.2.0.dist-info/METADATA
pf2e_wealth_calculator-0.2.0.dist-info/WHEEL
pf2e_wealth_calculator-0.2.0.dist-info/RECORD
