Metadata-Version: 2.1
Name: pf2e-wealth-calculator
Version: 0.2.0
Summary: A simple tool for Pathfinder 2e that calculates how much your loot is worth.
Home-page: https://github.com/D4wnstar/pf2e-wealth-calculator
License: GPL-3.0-or-later
Author: D4wnstar
Author-email: samvignoli@proton.me
Requires-Python: >=3.9,<4.0
Classifier: License :: OSI Approved :: GNU General Public License v3 or later (GPLv3+)
Classifier: Programming Language :: Python :: 3
Classifier: Programming Language :: Python :: 3.9
Classifier: Programming Language :: Python :: 3.10
Classifier: Programming Language :: Python :: 3.11
Requires-Dist: pandas (>=1.5.2,<2.0.0)
Requires-Dist: tabulate (>=0.9.0,<0.10.0)
Project-URL: Repository, https://github.com/D4wnstar/pf2e-wealth-calculator
